kfpdist/__init__.py
kfpdist/kfp_dist_step.py
kfpdist/set_tf_config.py
kfpdist-0.1.8.dist-info/METADATA
kfpdist-0.1.8.dist-info/WHEEL
kfpdist-0.1.8.dist-info/top_level.txt
kfpdist-0.1.8.dist-info/RECORD
