Metadata-Version: 2.1
Name: kfpdist
Version: 0.1.8
Summary: Use Kubeflow Pipeline to run distributed training jobs
Home-page: https://github.com/typhoonzero/kfp-dist-train
Author: typhoonzero
Author-email: typhoonzero@gmail.com
License: UNKNOWN
Project-URL: Bug Tracker, https://github.com/typhoonzero/kfp-dist-train/issues
Platform: UNKNOWN
Classifier: Programming Language :: Python :: 3
Classifier: License :: OSI Approved :: MIT License
Classifier: Operating System :: OS Independent
Requires-Python: >=3.6
Requires-Dist: kubernetes
Requires-Dist: kfp (==1.8.2)
